nvidia_tao_pytorch/__init__.py
nvidia_tao_pytorch/core/__init__.py
nvidia_tao_pytorch/core/checkpoint_encryption.py
nvidia_tao_pytorch/core/early_stopping.py
nvidia_tao_pytorch/core/entrypoint.py
nvidia_tao_pytorch/core/exp_manager.py
nvidia_tao_pytorch/core/initialize_experiments.py
nvidia_tao_pytorch/core/kenlma.py
nvidia_tao_pytorch/core/models.py
nvidia_tao_pytorch/core/path_utils.py
nvidia_tao_pytorch/core/platform_utils.py
nvidia_tao_pytorch/core/tlt_logging.py
nvidia_tao_pytorch/core/tokenizer.py
nvidia_tao_pytorch/core/utilities.py
nvidia_tao_pytorch/core/version.py
nvidia_tao_pytorch/core/callbacks/__init__.py
nvidia_tao_pytorch/core/callbacks/ema.py
nvidia_tao_pytorch/core/callbacks/loggers.py
nvidia_tao_pytorch/core/callbacks/model_checkpoint.py
nvidia_tao_pytorch/core/connectors/__init__.py
nvidia_tao_pytorch/core/connectors/checkpoint_connector.py
nvidia_tao_pytorch/core/cookbooks/__init__.py
nvidia_tao_pytorch/core/cookbooks/cookbook.py
nvidia_tao_pytorch/core/cookbooks/tlt_pytorch_cookbook.py
nvidia_tao_pytorch/core/cookbooks/vocabulary_cookbook.py
nvidia_tao_pytorch/core/decorators/__init__.py
nvidia_tao_pytorch/core/decorators/experimental.py
nvidia_tao_pytorch/core/decorators/workflow.py
nvidia_tao_pytorch/core/distillation/__init__.py
nvidia_tao_pytorch/core/distillation/distiller.py
nvidia_tao_pytorch/core/distillation/losses.py
nvidia_tao_pytorch/core/distillation/models.py
nvidia_tao_pytorch/core/distillation/utils.py
nvidia_tao_pytorch/core/distributed/__init__.py
nvidia_tao_pytorch/core/distributed/comm.py
nvidia_tao_pytorch/core/distributed/safe_unpickler.py
nvidia_tao_pytorch/core/distributed/serialized_object.py
nvidia_tao_pytorch/core/distributed/validator.py
nvidia_tao_pytorch/core/hydra/__init__.py
nvidia_tao_pytorch/core/hydra/hydra_runner.py
nvidia_tao_pytorch/core/lightning/__init__.py
nvidia_tao_pytorch/core/lightning/tao_lightning_module.py
nvidia_tao_pytorch/core/loggers/__init__.py
nvidia_tao_pytorch/core/loggers/api_logging.py
nvidia_tao_pytorch-6.25.11.dist-info/licenses/LICENSE
nvidia_tao_pytorch-6.25.11.dist-info/METADATA
nvidia_tao_pytorch-6.25.11.dist-info/WHEEL
nvidia_tao_pytorch-6.25.11.dist-info/entry_points.txt
nvidia_tao_pytorch-6.25.11.dist-info/top_level.txt
nvidia_tao_pytorch-6.25.11.dist-info/RECORD
