Metadata-Version: 2.4
Name: nvidia-tao-pytorch
Version: 6.25.11
Summary: NVIDIA's package for DNN implementation on PyTorch for use with TAO Toolkit.
Author: NVIDIA Corporation
License: NVIDIA Proprietary Software
Keywords: nvidia,tao,pytorch
Classifier: Environment :: Console
Classifier: License :: OSI Approved :: Apache Software License
Classifier: Natural Language :: English
Classifier: Operating System :: POSIX :: Linux
Classifier: Programming Language :: Python :: 3.12
Classifier: Topic :: Scientific/Engineering :: Artificial Intelligence
License-File: LICENSE
Dynamic: author
Dynamic: classifier
Dynamic: keywords
Dynamic: license
Dynamic: license-file
Dynamic: summary
